Workbook

Sheet Tabela_dinamica
A1: Tabela dinâmica: vendas por categoria e subcategoria, por região
A3: Soma de Vendas | B3: Column Labels
A4: Row Labels | B4: Central | C4: East | D4: South | E4: West | F4: Grand Total
A5: Furniture | B5: 163797.16 | C5: 208291.2 | D5: 117298.68 | E5: 252612.74 | F5: 741999.8
A6: Bookcases | B6: 24157.177 | C6: 43819.334 | D6: 10899.362 | E6: 36004.124 | F6: 114880
A7: Chairs | B7: 85230.646 | C7: 96260.683 | D7: 45176.446 | E7: 101781.33 | F7: 328449.1
A8: Furnishings | B8: 15254.37 | C8: 29071.38 | D8: 17306.684 | E8: 30072.73 | F8: 91705.164
A9: Tables | B9: 39154.971 | C9: 39139.807 | D9: 43916.192 | E9: 84754.562 | F9: 206965.53
A10: Office Supplies | B10: 167026.42 | C10: 205516.05 | D10: 125651.31 | E10: 220853.25 | F10: 719047.03
A11: Appliances | B11: 23582.033 | C11: 34188.466 | D11: 19525.326 | E11: 30236.336 | F11: 107532.16
A12: Art | B12: 5765.34 | C12: 7485.764 | D12: 4655.622 | E12: 9212.066 | F12: 27118.792
A13: Binders | B13: 56923.282 | C13: 53497.997 | D13: 37030.341 | E13: 55961.113 | F13: 203412.73
A14: Envelopes | B14: 4636.872 | C14: 4375.874 | D14: 3345.556 | E14: 4118.1 | F14: 16476.402
A15: Fasteners | B15: 778.03 | C15: 819.718 | D15: 503.316 | E15: 923.216 | F15: 3024.28
A16: Labels | B16: 2451.472 | C16: 2602.934 | D16: 2353.18 | E16: 5078.726 | F16: 12486.312
... A25: Grand Total | B25: 501239.89 | C25: 678781.24 | D25: 391721.91 | E25: 725457.82 | F25: 2297200.9

Sheet Resumo
A1: SuperStore — Produtos e Localizações
A3: Vendas totais | B3: =SUM(dados!$E$2:$E$9995) -> 2297200.9
A4: Lucro total | B4: =SUM(dados!$H$2:$H$9995) -> 286397.02
A5: Margem global | B5: =B4/B3 -> 0.12467217
A6: Nº de produtos | B6: =COUNTA(Produtos!A2:A1863) -> 1862
A7: Nº de produtos que geram 80% das vendas | B7: =SUMPRODUCT(--(Produtos!G2:G1863<=0.8))+1 -> 414
A8: % do catálogo que gera 80% das vendas | B8: =B7/B6 -> 0.22234157
A9: Nº de produtos com lucro total negativo | B9: =COUNTIF(Produtos!D2:D1863,"<0") -> 301
A12: Folhas
A13: dados: tabelão (orders + product + location) com a coluna Ano
A14: Categorias / Regioes / Cidades: tabelas SUMIFS e gráficos
A15: Produtos: ranking de todos os produtos, % acumulada (Pareto) e ranking
A16: Top_Bottom: 10 produtos com mais e com menos vendas
A17: Anos: vendas por ano

Sheet dados
A1: Order ID | B1: Order Date | C1: Customer ID | D1: Product ID | E1: Sales | F1: Quantity | G1: Discount | H1: Profit | I1: Category | J1: Sub-Category | K1: Product Name | L1: Region | M1: State | N1: City | O1: Ano
A2: CA-2016-152156 | B2: 42682 | C2: CG-12520 | D2: FUR-BO-10001798 | E2: 261.96 | F2: 2 | G2: 0 | H2: 41.9136 | I2: Furniture | J2: Bookcases | K2: Bush Somerset Collection Bookcase | L2: South | M2: Kentucky | N2: Henderson | O2: =YEAR(B2) -> 2016
A3: CA-2016-152156 | B3: 42682 | C3: CG-12520 | D3: FUR-CH-10000454 | E3: 731.94 | F3: 3 | G3: 0 | H3: 219.582 | I3: Furniture | J3: Chairs | K3: Hon Deluxe Fabric Upholstered Stacking Chairs, Rounded Back | L3: South | M3: Kentucky | N3: Henderson | O3: =YEAR(B3) -> 2016
A4: CA-2016-138688 | B4: 42533 | C4: DV-13045 | D4: OFF-LA-10000240 | E4: 14.62 | F4: 2 | G4: 0 | H4: 6.8714 | I4: Office Supplies | J4: Labels | K4: Self-Adhesive Address Labels for Typewriters by Universal | L4: West | M4: California | N4: Los Angeles | O4: =YEAR(B4) -> 2016
A5: US-2015-108966 | B5: 42288 | C5: SO-20335 | D5: FUR-TA-10000577 | E5: 957.5775 | F5: 5 | G5: 0.45 | H5: -383.031 | I5: Furniture | J5: Tables | K5: Bretford CR4500 Series Slim Rectangular Table | L5: South | M5: Florida | N5: Fort Lauderdale | O5: =YEAR(B5) -> 2015
A6: US-2015-108966 | B6: 42288 | C6: SO-20335 | D6: OFF-ST-10000760 | E6: 22.368 | F6: 2 | G6: 0.2 | H6: 2.5164 | I6: Office Supplies | J6: Storage | K6: Eldon Fold 'N Roll Cart System | L6: South | M6: Florida | N6: Fort Lauderdale | O6: =YEAR(B6) -> 2015
A7: CA-2014-115812 | B7: 41799 | C7: BH-11710 | D7: FUR-FU-10001487 | E7: 48.86 | F7: 7 | G7: 0 | H7: 14.1694 | I7: Furniture | J7: Furnishings | K7: Eldon Expressions Wood and Plastic Desk Accessories, Cherry Wood | L7: West | M7: California | N7: Los Angeles | O7: =YEAR(B7) -> 2014
A8: CA-2014-115812 | B8: 41799 | C8: BH-11710 | D8: OFF-AR-10002833 | E8: 7.28 | F8: 4 | G8: 0 | H8: 1.9656 | I8: Office Supplies | J8: Art | K8: Newell 322 | L8: West | M8: California | N8: Los Angeles | O8: =YEAR(B8) -> 2014
A9: CA-2014-115812 | B9: 41799 | C9: BH-11710 | D9: TEC-PH-10002275 | E9: 907.152 | F9: 6 | G9: 0.2 | H9: 90.7152 | I9: Technology | J9: Phones | K9: Mitel 5320 IP Phone VoIP phone | L9: West | M9: California | N9: Los Angeles | O9: =YEAR(B9) -> 2014
A10: CA-2014-115812 | B10: 41799 | C10: BH-11710 | D10: OFF-BI-10003910 | E10: 18.504 | F10: 3 | G10: 0.2 | H10: 5.7825 | I10: Office Supplies | J10: Binders | K10: DXL Angle-View Binders with Locking Rings by Samsill | L10: West | M10: California | N10: Los Angeles | O10: =YEAR(B10) -> 2014
A11: CA-2014-115812 | B11: 41799 | C11: BH-11710 | D11: OFF-AP-10002892 | E11: 114.9 | F11: 5 | G11: 0 | H11: 34.47 | I11: Office Supplies | J11: Appliances | K11: Belkin F5C206VTEL 6 Outlet Surge | L11: West | M11: California | N11: Los Angeles | O11: =YEAR(B11) -> 2014
A12: CA-2014-115812 | B12: 41799 | C12: BH-11710 | D12: FUR-TA-10001539 | E12: 1706.184 | F12: 9 | G12: 0.2 | H12: 85.3092 | I12: Furniture | J12: Tables | K12: Chromcraft Rectangular Conference Tables | L12: West | M12: California | N12: Los Angeles | O12: =YEAR(B12) -> 2014
A13: CA-2014-115812 | B13: 41799 | C13: BH-11710 | D13: TEC-PH-10002033 | E13: 911.424 | F13: 4 | G13: 0.2 | H13: 68.3568 | I13: Technology | J13: Phones | K13: Konftel 250 Conference phone - Charcoal black | L13: West | M13: California | N13: Los Angeles | O13: =YEAR(B13) -> 2014
... A9995: CA-2017-119914 | B9995: 42859 | C9995: CC-12220 | D9995: OFF-AP-10002684 | E9995: 243.16 | F9995: 2 | G9995: 0 | H9995: 72.948 | I9995: Office Supplies | J9995: Appliances | K9995: Acco 7-Outlet Masterpiece Power Center, Wihtout Fax/Phone Line Protection | L9995: West | M9995: California | N9995: Westminster | O9995: =YEAR(B9995) -> 2017

Sheet Categorias
A1: Vendas, lucro e margem por categoria e subcategoria
A3: Categoria | B3: Vendas | C3: % Vendas | D3: Lucro | E3: Margem | F3: % acumulada
A4: Technology | B4: =SUMIFS(dados!$E$2:$E$9995,dados!$I$2:$I$9995,A4) -> 836154.03 | C4: =B4/SUM($B$4:$B$6) -> 0.36398821 | D4: =SUMIFS(dados!$H$2:$H$9995,dados!$I$2:$I$9995,A4) -> 145454.95 | E4: =D4/B4 -> 0.17395712 | F4: =SUM($C$4:C4) -> 0.36398821
A5: Furniture | B5: =SUMIFS(dados!$E$2:$E$9995,dados!$I$2:$I$9995,A5) -> 741999.8 | C5: =B5/SUM($B$4:$B$6) -> 0.32300171 | D5: =SUMIFS(dados!$H$2:$H$9995,dados!$I$2:$I$9995,A5) -> 18451.273 | E5: =D5/B5 -> 0.024866951 | F5: =SUM($C$4:C5) -> 0.68698992
A6: Office Supplies | B6: =SUMIFS(dados!$E$2:$E$9995,dados!$I$2:$I$9995,A6) -> 719047.03 | C6: =B6/SUM($B$4:$B$6) -> 0.31301008 | D6: =SUMIFS(dados!$H$2:$H$9995,dados!$I$2:$I$9995,A6) -> 122490.8 | E6: =D6/B6 -> 0.17035158 | F6: =SUM($C$4:C6) -> 1
A7: Total | B7: =SUM(B4:B6) -> 2297200.9 | D7: =SUM(D4:D6) -> 286397.02 | E7: =D7/B7 -> 0.12467217
A10: Subcategoria | B10: Vendas | C10: % Vendas | D10: Lucro | E10: Margem | F10: % acumulada
A11: Phones | B11: =SUMIFS(dados!$E$2:$E$9995,dados!$J$2:$J$9995,A11) -> 330007.05 | C11: =B11/SUM($B$11:$B$27) -> 0.14365616 | D11: =SUMIFS(dados!$H$2:$H$9995,dados!$J$2:$J$9995,A11) -> 44515.731 | E11: =D11/B11 -> 0.13489327 | F11: =SUM($C$11:C11) -> 0.14365616
A12: Chairs | B12: =SUMIFS(dados!$E$2:$E$9995,dados!$J$2:$J$9995,A12) -> 328449.1 | C12: =B12/SUM($B$11:$B$27) -> 0.14297796 | D12: =SUMIFS(dados!$H$2:$H$9995,dados!$J$2:$J$9995,A12) -> 26590.166 | E12: =D12/B12 -> 0.080956733 | F12: =SUM($C$11:C12) -> 0.28663412
A13: Storage | B13: =SUMIFS(dados!$E$2:$E$9995,dados!$J$2:$J$9995,A13) -> 223843.61 | C13: =B13/SUM($B$11:$B$27) -> 0.097441896 | D13: =SUMIFS(dados!$H$2:$H$9995,dados!$J$2:$J$9995,A13) -> 21278.826 | E13: =D13/B13 -> 0.09506113 | F13: =SUM($C$11:C13) -> 0.38407602
A14: Tables | B14: =SUMIFS(dados!$E$2:$E$9995,dados!$J$2:$J$9995,A14) -> 206965.53 | C14: =B14/SUM($B$11:$B$27) -> 0.090094661 | D14: =SUMIFS(dados!$H$2:$H$9995,dados!$J$2:$J$9995,A14) -> -17725.481 | E14: =D14/B14 -> -0.085644604 | F14: =SUM($C$11:C14) -> 0.47417068
A15: Binders | B15: =SUMIFS(dados!$E$2:$E$9995,dados!$J$2:$J$9995,A15) -> 203412.73 | C15: =B15/SUM($B$11:$B$27) -> 0.088548083 | D15: =SUMIFS(dados!$H$2:$H$9995,dados!$J$2:$J$9995,A15) -> 30221.763 | E15: =D15/B15 -> 0.14857361 | F15: =SUM($C$11:C15) -> 0.56271876
A16: Machines | B16: =SUMIFS(dados!$E$2:$E$9995,dados!$J$2:$J$9995,A16) -> 189238.63 | C16: =B16/SUM($B$11:$B$27) -> 0.082377921 | D16: =SUMIFS(dados!$H$2:$H$9995,dados!$J$2:$J$9995,A16) -> 3384.7569 | E16: =D16/B16 -> 0.017886184 | F16: =SUM($C$11:C16) -> 0.64509669
A17: Accessories | B17: =SUMIFS(dados!$E$2:$E$9995,dados!$J$2:$J$9995,A17) -> 167380.32 | C17: =B17/SUM($B$11:$B$27) -> 0.072862727 | D17: =SUMIFS(dados!$H$2:$H$9995,dados!$J$2:$J$9995,A17) -> 41936.636 | E17: =D17/B17 -> 0.250547 | F17: =SUM($C$11:C17) -> 0.71795941
A18: Copiers | B18: =SUMIFS(dados!$E$2:$E$9995,dados!$J$2:$J$9995,A18) -> 149528.03 | C18: =B18/SUM($B$11:$B$27) -> 0.065091404 | D18: =SUMIFS(dados!$H$2:$H$9995,dados!$J$2:$J$9995,A18) -> 55617.825 | E18: =D18/B18 -> 0.37195585 | F18: =SUM($C$11:C18) -> 0.78305082
A19: Bookcases | B19: =SUMIFS(dados!$E$2:$E$9995,dados!$J$2:$J$9995,A19) -> 114880 | C19: =B19/SUM($B$11:$B$27) -> 0.050008686 | D19: =SUMIFS(dados!$H$2:$H$9995,dados!$J$2:$J$9995,A19) -> -3472.556 | E19: =D19/B19 -> -0.030227682 | F19: =SUM($C$11:C19) -> 0.8330595
A20: Appliances | B20: =SUMIFS(dados!$E$2:$E$9995,dados!$J$2:$J$9995,A20) -> 107532.16 | C20: =B20/SUM($B$11:$B$27) -> 0.046810082 | D20: =SUMIFS(dados!$H$2:$H$9995,dados!$J$2:$J$9995,A20) -> 18138.005 | E20: =D20/B20 -> 0.16867517 | F20: =SUM($C$11:C20) -> 0.87986958
A21: Furnishings | B21: =SUMIFS(dados!$E$2:$E$9995,dados!$J$2:$J$9995,A21) -> 91705.164 | C21: =B21/SUM($B$11:$B$27) -> 0.039920394 | D21: =SUMIFS(dados!$H$2:$H$9995,dados!$J$2:$J$9995,A21) -> 13059.144 | E21: =D21/B21 -> 0.14240358 | F21: =SUM($C$11:C21) -> 0.91978998
A22: Paper | B22: =SUMIFS(dados!$E$2:$E$9995,dados!$J$2:$J$9995,A22) -> 78479.206 | C22: =B22/SUM($B$11:$B$27) -> 0.034162971 | D22: =SUMIFS(dados!$H$2:$H$9995,dados!$J$2:$J$9995,A22) -> 34053.569 | E22: =D22/B22 -> 0.43391837 | F22: =SUM($C$11:C22) -> 0.95395295
... A27: Fasteners | B27: =SUMIFS(dados!$E$2:$E$9995,dados!$J$2:$J$9995,A27) -> 3024.28 | C27: =B27/SUM($B$11:$B$27) -> 0.0013165066 | D27: =SUMIFS(dados!$H$2:$H$9995,dados!$J$2:$J$9995,A27) -> 949.5182 | E27: =D27/B27 -> 0.31396504 | F27: =SUM($C$11:C27) -> 1
A28: Total | B28: =SUM(B11:B27) -> 2297200.9 | D28: =SUM(D11:D27) -> 286397.02 | E28: =D28/B28 -> 0.12467217

Sheet Regioes
A1: Vendas, lucro e margem por região, estado e cidade
A3: Região | B3: Vendas | C3: % Vendas | D3: Lucro | E3: Margem | F3: % acumulada
A4: West | B4: =SUMIFS(dados!$E$2:$E$9995,dados!$L$2:$L$9995,A4) -> 725457.82 | C4: =B4/SUM($B$4:$B$7) -> 0.31580078 | D4: =SUMIFS(dados!$H$2:$H$9995,dados!$L$2:$L$9995,A4) -> 108418.45 | E4: =D4/B4 -> 0.14944831 | F4: =SUM($C$4:C4) -> 0.31580078
A5: East | B5: =SUMIFS(dados!$E$2:$E$9995,dados!$L$2:$L$9995,A5) -> 678781.24 | C5: =B5/SUM($B$4:$B$7) -> 0.29548188 | D5: =SUMIFS(dados!$H$2:$H$9995,dados!$L$2:$L$9995,A5) -> 91522.78 | E5: =D5/B5 -> 0.13483399 | F5: =SUM($C$4:C5) -> 0.61128267
A6: Central | B6: =SUMIFS(dados!$E$2:$E$9995,dados!$L$2:$L$9995,A6) -> 501239.89 | C6: =B6/SUM($B$4:$B$7) -> 0.21819594 | D6: =SUMIFS(dados!$H$2:$H$9995,dados!$L$2:$L$9995,A6) -> 39706.362 | E6: =D6/B6 -> 0.079216286 | F6: =SUM($C$4:C6) -> 0.8294786
A7: South | B7: =SUMIFS(dados!$E$2:$E$9995,dados!$L$2:$L$9995,A7) -> 391721.91 | C7: =B7/SUM($B$4:$B$7) -> 0.1705214 | D7: =SUMIFS(dados!$H$2:$H$9995,dados!$L$2:$L$9995,A7) -> 46749.43 | E7: =D7/B7 -> 0.11934342 | F7: =SUM($C$4:C7) -> 1
A8: Total | B8: =SUM(B4:B7) -> 2297200.9 | D8: =SUM(D4:D7) -> 286397.02 | E8: =D8/B8 -> 0.12467217
A11: Estado | B11: Vendas | C11: % Vendas | D11: Lucro | E11: Margem | F11: % acumulada
A12: California | B12: =SUMIFS(dados!$E$2:$E$9995,dados!$M$2:$M$9995,A12) -> 457687.63 | C12: =B12/SUM($B$12:$B$60) -> 0.1992371 | D12: =SUMIFS(dados!$H$2:$H$9995,dados!$M$2:$M$9995,A12) -> 76381.387 | E12: =D12/B12 -> 0.16688541 | F12: =SUM($C$12:C12) -> 0.1992371
A13: New York | B13: =SUMIFS(dados!$E$2:$E$9995,dados!$M$2:$M$9995,A13) -> 310876.27 | C13: =B13/SUM($B$12:$B$60) -> 0.13532829 | D13: =SUMIFS(dados!$H$2:$H$9995,dados!$M$2:$M$9995,A13) -> 74038.549 | E13: =D13/B13 -> 0.23816082 | F13: =SUM($C$12:C13) -> 0.33456539
A14: Texas | B14: =SUMIFS(dados!$E$2:$E$9995,dados!$M$2:$M$9995,A14) -> 170188.05 | C14: =B14/SUM($B$12:$B$60) -> 0.074084965 | D14: =SUMIFS(dados!$H$2:$H$9995,dados!$M$2:$M$9995,A14) -> -25729.356 | E14: =D14/B14 -> -0.15118192 | F14: =SUM($C$12:C14) -> 0.40865036
A15: Washington | B15: =SUMIFS(dados!$E$2:$E$9995,dados!$M$2:$M$9995,A15) -> 138641.27 | C15: =B15/SUM($B$12:$B$60) -> 0.060352263 | D15: =SUMIFS(dados!$H$2:$H$9995,dados!$M$2:$M$9995,A15) -> 33402.652 | E15: =D15/B15 -> 0.24092863 | F15: =SUM($C$12:C15) -> 0.46900262
A16: Pennsylvania | B16: =SUMIFS(dados!$E$2:$E$9995,dados!$M$2:$M$9995,A16) -> 116511.91 | C16: =B16/SUM($B$12:$B$60) -> 0.05071908 | D16: =SUMIFS(dados!$H$2:$H$9995,dados!$M$2:$M$9995,A16) -> -15559.96 | E16: =D16/B16 -> -0.13354823 | F16: =SUM($C$12:C16) -> 0.5197217
A17: Florida | B17: =SUMIFS(dados!$E$2:$E$9995,dados!$M$2:$M$9995,A17) -> 89473.708 | C17: =B17/SUM($B$12:$B$60) -> 0.038949014 | D17: =SUMIFS(dados!$H$2:$H$9995,dados!$M$2:$M$9995,A17) -> -3399.3017 | E17: =D17/B17 -> -0.037992185 | F17: =SUM($C$12:C17) -> 0.55867071
A18: Illinois | B18: =SUMIFS(dados!$E$2:$E$9995,dados!$M$2:$M$9995,A18) -> 80166.101 | C18: =B18/SUM($B$12:$B$60) -> 0.034897297 | D18: =SUMIFS(dados!$H$2:$H$9995,dados!$M$2:$M$9995,A18) -> -12607.887 | E18: =D18/B18 -> -0.15727205 | F18: =SUM($C$12:C18) -> 0.59356801
A19: Ohio | B19: =SUMIFS(dados!$E$2:$E$9995,dados!$M$2:$M$9995,A19) -> 78258.136 | C19: =B19/SUM($B$12:$B$60) -> 0.034066736 | D19: =SUMIFS(dados!$H$2:$H$9995,dados!$M$2:$M$9995,A19) -> -16971.377 | E19: =D19/B19 -> -0.21686405 | F19: =SUM($C$12:C19) -> 0.62763475
A20: Michigan | B20: =SUMIFS(dados!$E$2:$E$9995,dados!$M$2:$M$9995,A20) -> 76269.614 | C20: =B20/SUM($B$12:$B$60) -> 0.033201108 | D20: =SUMIFS(dados!$H$2:$H$9995,dados!$M$2:$M$9995,A20) -> 24463.188 | E20: =D20/B20 -> 0.32074618 | F20: =SUM($C$12:C20) -> 0.66083585
A21: Virginia | B21: =SUMIFS(dados!$E$2:$E$9995,dados!$M$2:$M$9995,A21) -> 70636.72 | C21: =B21/SUM($B$12:$B$60) -> 0.03074904 | D21: =SUMIFS(dados!$H$2:$H$9995,dados!$M$2:$M$9995,A21) -> 18597.95 | E21: =D21/B21 -> 0.26329012 | F21: =SUM($C$12:C21) -> 0.69158489
A22: North Carolina | B22: =SUMIFS(dados!$E$2:$E$9995,dados!$M$2:$M$9995,A22) -> 55603.164 | C22: =B22/SUM($B$12:$B$60) -> 0.024204746 | D22: =SUMIFS(dados!$H$2:$H$9995,dados!$M$2:$M$9995,A22) -> -7490.9122 | E22: =D22/B22 -> -0.13472097 | F22: =SUM($C$12:C22) -> 0.71578964
A23: Indiana | B23: =SUMIFS(dados!$E$2:$E$9995,dados!$M$2:$M$9995,A23) -> 53555.36 | C23: =B23/SUM($B$12:$B$60) -> 0.023313312 | D23: =SUMIFS(dados!$H$2:$H$9995,dados!$M$2:$M$9995,A23) -> 18382.936 | E23: =D23/B23 -> 0.3432511 | F23: =SUM($C$12:C23) -> 0.73910295
... A60: North Dakota | B60: =SUMIFS(dados!$E$2:$E$9995,dados!$M$2:$M$9995,A60) -> 919.91 | C60: =B60/SUM($B$12:$B$60) -> 0.00040044822 | D60: =SUMIFS(dados!$H$2:$H$9995,dados!$M$2:$M$9995,A60) -> 230.1497 | E60: =D60/B60 -> 0.25018719 | F60: =SUM($C$12:C60) -> 1
A61: Total | B61: =SUM(B12:B60) -> 2297200.9 | D61: =SUM(D12:D60) -> 286397.02 | E61: =D61/B61 -> 0.12467217

Sheet Cidades
A1: Vendas, lucro e margem por cidade (ordenadas por vendas)
A3: Cidade | B3: Vendas | C3: % Vendas | D3: Lucro | E3: Margem | F3: % acumulada
A4: New York City | B4: =SUMIFS(dados!$E$2:$E$9995,dados!$N$2:$N$9995,A4) -> 256368.16 | C4: =B4/SUM($B$4:$B$534) -> 0.11160024 | D4: =SUMIFS(dados!$H$2:$H$9995,dados!$N$2:$N$9995,A4) -> 62036.984 | E4: =D4/B4 -> 0.24198396 | F4: =SUM($C$4:C4) -> 0.11160024
A5: Los Angeles | B5: =SUMIFS(dados!$E$2:$E$9995,dados!$N$2:$N$9995,A5) -> 175851.34 | C5: =B5/SUM($B$4:$B$534) -> 0.076550268 | D5: =SUMIFS(dados!$H$2:$H$9995,dados!$N$2:$N$9995,A5) -> 30440.758 | E5: =D5/B5 -> 0.17310507 | F5: =SUM($C$4:C5) -> 0.18815051
A6: Seattle | B6: =SUMIFS(dados!$E$2:$E$9995,dados!$N$2:$N$9995,A6) -> 119540.74 | C6: =B6/SUM($B$4:$B$534) -> 0.052037566 | D6: =SUMIFS(dados!$H$2:$H$9995,dados!$N$2:$N$9995,A6) -> 29156.097 | E6: =D6/B6 -> 0.24390092 | F6: =SUM($C$4:C6) -> 0.24018807
A7: San Francisco | B7: =SUMIFS(dados!$E$2:$E$9995,dados!$N$2:$N$9995,A7) -> 112669.09 | C7: =B7/SUM($B$4:$B$534) -> 0.049046252 | D7: =SUMIFS(dados!$H$2:$H$9995,dados!$N$2:$N$9995,A7) -> 17507.385 | E7: =D7/B7 -> 0.15538765 | F7: =SUM($C$4:C7) -> 0.28923432
A8: Philadelphia | B8: =SUMIFS(dados!$E$2:$E$9995,dados!$N$2:$N$9995,A8) -> 109077.01 | C8: =B8/SUM($B$4:$B$534) -> 0.047482575 | D8: =SUMIFS(dados!$H$2:$H$9995,dados!$N$2:$N$9995,A8) -> -13837.767 | E8: =D8/B8 -> -0.12686236 | F8: =SUM($C$4:C8) -> 0.3367169
A9: Houston | B9: =SUMIFS(dados!$E$2:$E$9995,dados!$N$2:$N$9995,A9) -> 64504.76 | C9: =B9/SUM($B$4:$B$534) -> 0.028079722 | D9: =SUMIFS(dados!$H$2:$H$9995,dados!$N$2:$N$9995,A9) -> -10153.548 | E9: =D9/B9 -> -0.15740774 | F9: =SUM($C$4:C9) -> 0.36479662
A10: Chicago | B10: =SUMIFS(dados!$E$2:$E$9995,dados!$N$2:$N$9995,A10) -> 48539.541 | C10: =B10/SUM($B$4:$B$534) -> 0.021129864 | D10: =SUMIFS(dados!$H$2:$H$9995,dados!$N$2:$N$9995,A10) -> -6654.5688 | E10: =D10/B10 -> -0.13709583 | F10: =SUM($C$4:C10) -> 0.38592648
A11: San Diego | B11: =SUMIFS(dados!$E$2:$E$9995,dados!$N$2:$N$9995,A11) -> 47521.029 | C11: =B11/SUM($B$4:$B$534) -> 0.020686493 | D11: =SUMIFS(dados!$H$2:$H$9995,dados!$N$2:$N$9995,A11) -> 6377.196 | E11: =D11/B11 -> 0.13419735 | F11: =SUM($C$4:C11) -> 0.40661298
A12: Jacksonville | B12: =SUMIFS(dados!$E$2:$E$9995,dados!$N$2:$N$9995,A12) -> 44713.183 | C12: =B12/SUM($B$4:$B$534) -> 0.019464203 | D12: =SUMIFS(dados!$H$2:$H$9995,dados!$N$2:$N$9995,A12) -> -2323.835 | E12: =D12/B12 -> -0.051972032 | F12: =SUM($C$4:C12) -> 0.42607718
A13: Springfield | B13: =SUMIFS(dados!$E$2:$E$9995,dados!$N$2:$N$9995,A13) -> 43054.342 | C13: =B13/SUM($B$4:$B$534) -> 0.018742089 | D13: =SUMIFS(dados!$H$2:$H$9995,dados!$N$2:$N$9995,A13) -> 6200.6974 | E13: =D13/B13 -> 0.14402026 | F13: =SUM($C$4:C13) -> 0.44481927
A14: Detroit | B14: =SUMIFS(dados!$E$2:$E$9995,dados!$N$2:$N$9995,A14) -> 42446.944 | C14: =B14/SUM($B$4:$B$534) -> 0.018477681 | D14: =SUMIFS(dados!$H$2:$H$9995,dados!$N$2:$N$9995,A14) -> 13181.791 | E14: =D14/B14 -> 0.31054746 | F14: =SUM($C$4:C14) -> 0.46329695
A15: Columbus | B15: =SUMIFS(dados!$E$2:$E$9995,dados!$N$2:$N$9995,A15) -> 38706.243 | C15: =B15/SUM($B$4:$B$534) -> 0.016849307 | D15: =SUMIFS(dados!$H$2:$H$9995,dados!$N$2:$N$9995,A15) -> 5897.1013 | E15: =D15/B15 -> 0.1523553 | F15: =SUM($C$4:C15) -> 0.48014626
... A534: Abilene | B534: =SUMIFS(dados!$E$2:$E$9995,dados!$N$2:$N$9995,A534) -> 1.392 | C534: =B534/SUM($B$4:$B$534) -> 6.0595485e-07 | D534: =SUMIFS(dados!$H$2:$H$9995,dados!$N$2:$N$9995,A534) -> -3.7584 | E534: =D534/B534 -> -2.7 | F534: =SUM($C$4:C534) -> 1
A535: Total | B535: =SUM(B4:B534) -> 2297200.9 | D535: =SUM(D4:D534) -> 286397.02 | E535: =D535/B535 -> 0.12467217

Sheet Produtos
A1: Product ID | B1: Produto | C1: Vendas | D1: Lucro | E1: Margem | F1: % Vendas | G1: % acumulada (Pareto) | H1: Ranking
A2: TEC-CO-10004722 | B2: Canon imageCLASS 2200 Advanced Copier | C2: =SUMIFS(dados!$E$2:$E$9995,dados!$D$2:$D$9995,A2) -> 61599.824 | D2: =SUMIFS(dados!$H$2:$H$9995,dados!$D$2:$D$9995,A2) -> 25199.928 | E2: =IFERROR(D2/C2,0) -> 0.40909091 | F2: =C2/SUM($C$2:$C$1863) -> 0.026815167 | G2: =SUM($F$2:F2) -> 0.026815167 | H2: =RANK(C2,$C$2:$C$1863) -> 1
A3: OFF-BI-10003527 | B3: Fellowes PB500 Electric Punch Plastic Comb Binding Machine with Manual Bind | C3: =SUMIFS(dados!$E$2:$E$9995,dados!$D$2:$D$9995,A3) -> 27453.384 | D3: =SUMIFS(dados!$H$2:$H$9995,dados!$D$2:$D$9995,A3) -> 7753.039 | E3: =IFERROR(D3/C3,0) -> 0.28240741 | F3: =C3/SUM($C$2:$C$1863) -> 0.011950798 | G3: =SUM($F$2:F3) -> 0.038765965 | H3: =RANK(C3,$C$2:$C$1863) -> 2
A4: TEC-MA-10002412 | B4: Cisco TelePresence System EX90 Videoconferencing Unit | C4: =SUMIFS(dados!$E$2:$E$9995,dados!$D$2:$D$9995,A4) -> 22638.48 | D4: =SUMIFS(dados!$H$2:$H$9995,dados!$D$2:$D$9995,A4) -> -1811.0784 | E4: =IFERROR(D4/C4,0) -> -0.08 | F4: =C4/SUM($C$2:$C$1863) -> 0.0098548109 | G4: =SUM($F$2:F4) -> 0.048620776 | H4: =RANK(C4,$C$2:$C$1863) -> 3
A5: FUR-CH-10002024 | B5: HON 5400 Series Task Chairs for Big and Tall | C5: =SUMIFS(dados!$E$2:$E$9995,dados!$D$2:$D$9995,A5) -> 21870.576 | D5: =SUMIFS(dados!$H$2:$H$9995,dados!$D$2:$D$9995,A5) -> 5.6843419e-14 | E5: =IFERROR(D5/C5,0) -> 2.5990819e-18 | F5: =C5/SUM($C$2:$C$1863) -> 0.0095205327 | G5: =SUM($F$2:F5) -> 0.058141309 | H5: =RANK(C5,$C$2:$C$1863) -> 4
A6: OFF-BI-10001359 | B6: GBC DocuBind TL300 Electric Binding System | C6: =SUMIFS(dados!$E$2:$E$9995,dados!$D$2:$D$9995,A6) -> 19823.479 | D6: =SUMIFS(dados!$H$2:$H$9995,dados!$D$2:$D$9995,A6) -> 2233.5051 | E6: =IFERROR(D6/C6,0) -> 0.11266968 | F6: =C6/SUM($C$2:$C$1863) -> 0.008629406 | G6: =SUM($F$2:F6) -> 0.066770715 | H6: =RANK(C6,$C$2:$C$1863) -> 5
A7: OFF-BI-10000545 | B7: GBC Ibimaster 500 Manual ProClick Binding System | C7: =SUMIFS(dados!$E$2:$E$9995,dados!$D$2:$D$9995,A7) -> 19024.5 | D7: =SUMIFS(dados!$H$2:$H$9995,dados!$D$2:$D$9995,A7) -> 760.98 | E7: =IFERROR(D7/C7,0) -> 0.04 | F7: =C7/SUM($C$2:$C$1863) -> 0.0082816006 | G7: =SUM($F$2:F7) -> 0.075052315 | H7: =RANK(C7,$C$2:$C$1863) -> 6
A8: TEC-CO-10001449 | B8: Hewlett Packard LaserJet 3310 Copier | C8: =SUMIFS(dados!$E$2:$E$9995,dados!$D$2:$D$9995,A8) -> 18839.686 | D8: =SUMIFS(dados!$H$2:$H$9995,dados!$D$2:$D$9995,A8) -> 6983.8836 | E8: =IFERROR(D8/C8,0) -> 0.37070064 | F8: =C8/SUM($C$2:$C$1863) -> 0.0082011488 | G8: =SUM($F$2:F8) -> 0.083253464 | H8: =RANK(C8,$C$2:$C$1863) -> 7
A9: TEC-MA-10001127 | B9: HP Designjet T520 Inkjet Large Format Printer - 24" Color | C9: =SUMIFS(dados!$E$2:$E$9995,dados!$D$2:$D$9995,A9) -> 18374.895 | D9: =SUMIFS(dados!$H$2:$H$9995,dados!$D$2:$D$9995,A9) -> 4094.9766 | E9: =IFERROR(D9/C9,0) -> 0.22285714 | F9: =C9/SUM($C$2:$C$1863) -> 0.0079988195 | G9: =SUM($F$2:F9) -> 0.091252283 | H9: =RANK(C9,$C$2:$C$1863) -> 8
A10: OFF-BI-10004995 | B10: GBC DocuBind P400 Electric Binding System | C10: =SUMIFS(dados!$E$2:$E$9995,dados!$D$2:$D$9995,A10) -> 17965.068 | D10: =SUMIFS(dados!$H$2:$H$9995,dados!$D$2:$D$9995,A10) -> -1878.1662 | E10: =IFERROR(D10/C10,0) -> -0.10454545 | F10: =C10/SUM($C$2:$C$1863) -> 0.0078204167 | G10: =SUM($F$2:F10) -> 0.0990727 | H10: =RANK(C10,$C$2:$C$1863) -> 9
A11: OFF-SU-10000151 | B11: High Speed Automatic Electric Letter Opener | C11: =SUMIFS(dados!$E$2:$E$9995,dados!$D$2:$D$9995,A11) -> 17030.312 | D11: =SUMIFS(dados!$H$2:$H$9995,dados!$D$2:$D$9995,A11) -> -262.0048 | E11: =IFERROR(D11/C11,0) -> -0.015384615 | F11: =C11/SUM($C$2:$C$1863) -> 0.0074135058 | G11: =SUM($F$2:F11) -> 0.10648621 | H11: =RANK(C11,$C$2:$C$1863) -> 10
A12: TEC-MA-10000822 | B12: Lexmark MX611dhe Monochrome Laser Printer | C12: =SUMIFS(dados!$E$2:$E$9995,dados!$D$2:$D$9995,A12) -> 16829.901 | D12: =SUMIFS(dados!$H$2:$H$9995,dados!$D$2:$D$9995,A12) -> -4589.973 | E12: =IFERROR(D12/C12,0) -> -0.27272727 | F12: =C12/SUM($C$2:$C$1863) -> 0.0073262645 | G12: =SUM($F$2:F12) -> 0.11381247 | H12: =RANK(C12,$C$2:$C$1863) -> 11
A13: OFF-SU-10002881 | B13: Martin Yale Chadless Opener Electric Letter Opener | C13: =SUMIFS(dados!$E$2:$E$9995,dados!$D$2:$D$9995,A13) -> 16656.2 | D13: =SUMIFS(dados!$H$2:$H$9995,dados!$D$2:$D$9995,A13) -> -1299.1836 | E13: =IFERROR(D13/C13,0) -> -0.078 | F13: =C13/SUM($C$2:$C$1863) -> 0.0072506503 | G13: =SUM($F$2:F13) -> 0.12106312 | H13: =RANK(C13,$C$2:$C$1863) -> 12
... A1863: OFF-AP-10002203 | B1863: Eureka Disposable Bags for Sanitaire Vibra Groomer I Upright Vac | C1863: =SUMIFS(dados!$E$2:$E$9995,dados!$D$2:$D$9995,A1863) -> 1.624 | D1863: =SUMIFS(dados!$H$2:$H$9995,dados!$D$2:$D$9995,A1863) -> -4.466 | E1863: =IFERROR(D1863/C1863,0) -> -2.75 | F1863: =C1863/SUM($C$2:$C$1863) -> 7.0694732e-07 | G1863: =SUM($F$2:F1863) -> 1 | H1863: =RANK(C1863,$C$2:$C$1863) -> 1862

Sheet Top_Bottom
A1: 10 produtos com mais e com menos vendas
A3: Mais vendas | B3: Vendas | C3: Lucro
A4: =Produtos!B2 -> Canon imageCLASS 2200 Advanced Copier | B4: =Produtos!C2 -> 61599.824 | C4: =Produtos!D2 -> 25199.928
A5: =Produtos!B3 -> Fellowes PB500 Electric Punch Plastic Comb Binding Machine with Manual Bind | B5: =Produtos!C3 -> 27453.384 | C5: =Produtos!D3 -> 7753.039
A6: =Produtos!B4 -> Cisco TelePresence System EX90 Videoconferencing Unit | B6: =Produtos!C4 -> 22638.48 | C6: =Produtos!D4 -> -1811.0784
A7: =Produtos!B5 -> HON 5400 Series Task Chairs for Big and Tall | B7: =Produtos!C5 -> 21870.576 | C7: =Produtos!D5 -> 5.6843419e-14
A8: =Produtos!B6 -> GBC DocuBind TL300 Electric Binding System | B8: =Produtos!C6 -> 19823.479 | C8: =Produtos!D6 -> 2233.5051
A9: =Produtos!B7 -> GBC Ibimaster 500 Manual ProClick Binding System | B9: =Produtos!C7 -> 19024.5 | C9: =Produtos!D7 -> 760.98
A10: =Produtos!B8 -> Hewlett Packard LaserJet 3310 Copier | B10: =Produtos!C8 -> 18839.686 | C10: =Produtos!D8 -> 6983.8836
A11: =Produtos!B9 -> HP Designjet T520 Inkjet Large Format Printer - 24" Color | B11: =Produtos!C9 -> 18374.895 | C11: =Produtos!D9 -> 4094.9766
A12: =Produtos!B10 -> GBC DocuBind P400 Electric Binding System | B12: =Produtos!C10 -> 17965.068 | C12: =Produtos!D10 -> -1878.1662
A13: =Produtos!B11 -> High Speed Automatic Electric Letter Opener | B13: =Produtos!C11 -> 17030.312 | C13: =Produtos!D11 -> -262.0048
A16: Menos vendas | B16: Vendas | C16: Lucro
A17: =Produtos!B1854 -> Avery 484 | B17: =Produtos!C1854 -> 9.216 | C17: =Produtos!D1854 -> 3.3408
A18: =Produtos!B1855 -> Newell 308 | B18: =Produtos!C1855 -> 8.4 | C18: =Produtos!D1855 -> 2.1
A19: =Produtos!B1856 -> Stockwell Gold Paper Clips | B19: =Produtos!C1856 -> 8.096 | C19: =Produtos!D1856 -> 3.404
A20: =Produtos!B1857 -> 4009 Highlighters | B20: =Produtos!C1857 -> 8.04 | C20: =Produtos!D1857 -> 2.7336
A21: =Produtos!B1858 -> Xerox 1989 | B21: =Produtos!C1858 -> 7.968 | C21: =Produtos!D1858 -> 2.6892
A22: =Produtos!B1859 -> Avery Hi-Liter Pen Style Six-Color Fluorescent Set | B22: =Produtos!C1859 -> 7.7 | C22: =Produtos!D1859 -> 3.157
A23: =Produtos!B1860 -> Grip Seal Envelopes | B23: =Produtos!C1860 -> 7.072 | C23: =Produtos!D1860 -> 2.3868
A24: =Produtos!B1861 -> Xerox 20 | B24: =Produtos!C1861 -> 6.48 | C24: =Produtos!D1861 -> 3.1104
A25: =Produtos!B1862 -> Avery 5 | B25: =Produtos!C1862 -> 5.76 | C25: =Produtos!D1862 -> 2.8224
A26: =Produtos!B1863 -> Eureka Disposable Bags for Sanitaire Vibra Groomer I Upright Vac | B26: =Produtos!C1863 -> 1.624 | C26: =Produtos!D1863 -> -4.466

Sheet Anos
A1: Vendas por ano
A3: Ano | B3: Vendas | C3: % Vendas | D3: Lucro
A4: 2014 | B4: =SUMIFS(dados!$E$2:$E$9995,dados!$O$2:$O$9995,A4) -> 484247.5 | C4: =B4/SUM($B$4:$B$7) -> 0.21079894 | D4: =SUMIFS(dados!$H$2:$H$9995,dados!$O$2:$O$9995,A4) -> 49543.974
A5: 2015 | B5: =SUMIFS(dados!$E$2:$E$9995,dados!$O$2:$O$9995,A5) -> 470532.51 | C5: =B5/SUM($B$4:$B$7) -> 0.20482863 | D5: =SUMIFS(dados!$H$2:$H$9995,dados!$O$2:$O$9995,A5) -> 61618.604
A6: 2016 | B6: =SUMIFS(dados!$E$2:$E$9995,dados!$O$2:$O$9995,A6) -> 609205.6 | C6: =B6/SUM($B$4:$B$7) -> 0.26519475 | D6: =SUMIFS(dados!$H$2:$H$9995,dados!$O$2:$O$9995,A6) -> 81795.174
A7: 2017 | B7: =SUMIFS(dados!$E$2:$E$9995,dados!$O$2:$O$9995,A7) -> 733215.26 | C7: =B7/SUM($B$4:$B$7) -> 0.31917769 | D7: =SUMIFS(dados!$H$2:$H$9995,dados!$O$2:$O$9995,A7) -> 93439.27
